{"frames": {

"1573_2_0.png":
{
	"frame": {"x":0,"y":0,"w":384,"h":128},
	"rotated": false,
	"trimmed": false,
	"spriteSourceSize": {"x":0,"y":0,"w":384,"h":128},
	"sourceSize": {"w":384,"h":128}
},
"1573_5_0.png":
{
	"frame": {"x":0,"y":128,"w":384,"h":128},
	"rotated": false,
	"trimmed": false,
	"spriteSourceSize": {"x":0,"y":0,"w":384,"h":128},
	"sourceSize": {"w":384,"h":128}
},
"1574_0_0.png":
{
	"frame": {"x":0,"y":256,"w":384,"h":128},
	"rotated": false,
	"trimmed": false,
	"spriteSourceSize": {"x":0,"y":0,"w":384,"h":128},
	"sourceSize": {"w":384,"h":128}
}},
"meta": {
	"app": "https://www.codeandweb.com/texturepacker",
	"version": "1.0",
	"image": "01_network.png",
	"format": "RGBA8888",
	"size": {"w":384,"h":384},
	"scale": "1",
	"smartupdate": "$TexturePacker:SmartUpdate:1bd7107f6b8d448fb0fc5c47cec93ece:2103bd86202fd715697e5471949c1f47:4cdd66a0ef91ef3fd1a4d4c3426bbb02$"
}
}
